.gitignore
.travis.yml
CHANGELOG.md
LICENSE
Makefile
README.md
mkdocs.yaml
requirements-dev.txt
requirements.txt
setup.cfg
setup.py
.github/pull_request_template.md
.github/workflows/python_unittest.yaml
benchmarks/README.md
benchmarks/benchmark.py
benchmarks/requirements.txt
benchmarks/run_atari.sh
benchmarks/run_pybullet.sh
benchmarks/run_spinup.sh
benchmarks/run_tabular.sh
cerise.egg-info/PKG-INFO
cerise.egg-info/SOURCES.txt
cerise.egg-info/dependency_links.txt
cerise.egg-info/requires.txt
cerise.egg-info/top_level.txt
cherry/__init__.py
cherry/_torch.py
cherry/_utils.py
cherry/_version.py
cherry/debug.py
cherry/distributions.py
cherry/experience_replay.py
cherry/optim.py
cherry/pg.py
cherry/plot.py
cherry/td.py
cherry/algorithms/__init__.py
cherry/algorithms/a2c.py
cherry/algorithms/arguments.py
cherry/algorithms/ddpg.py
cherry/algorithms/drq.py
cherry/algorithms/drqv2.py
cherry/algorithms/ppo.py
cherry/algorithms/sac.py
cherry/algorithms/td3.py
cherry/algorithms/trpo.py
cherry/envs/__init__.py
cherry/envs/utils.py
cherry/models/__init__.py
cherry/models/atari.py
cherry/models/robotics.py
cherry/models/tabular.py
cherry/models/utils.py
cherry/nn/__init__.py
cherry/nn/action_value.py
cherry/nn/epsilon_greedy.py
cherry/nn/init.py
cherry/nn/misc.py
cherry/nn/mlp.py
cherry/nn/policy.py
cherry/nn/robotics_layers.py
cherry/nn/state_value.py
cherry/wrappers/__init__.py
cherry/wrappers/action_lambda_wrapper.py
cherry/wrappers/action_space_scaler_wrapper.py
cherry/wrappers/base_wrapper.py
cherry/wrappers/closer.py
cherry/wrappers/logger_wrapper.py
cherry/wrappers/monitor_wrapper.py
cherry/wrappers/normalizer_wrapper.py
cherry/wrappers/openai_atari_wrapper.py
cherry/wrappers/recorder_wrapper.py
cherry/wrappers/reward_clipper_wrapper.py
cherry/wrappers/reward_normalizer_wrapper.py
cherry/wrappers/runner_wrapper.py
cherry/wrappers/state_lambda_wrapper.py
cherry/wrappers/state_normalizer_wrapper.py
cherry/wrappers/timestep_wrapper.py
cherry/wrappers/torch_wrapper.py
cherry/wrappers/visdom_logger_wrapper.py
docs/CNAME
docs/changelog.md
docs/index.md
docs/api/cherry.algorithms.md
docs/api/cherry.debug.md
