Metadata-Version: 2.1
Name: cerise
Version: 0.2.0
Summary: PyTorch Reinforcement Learning Framework for Researchers
Home-page: https://learnables.github.com/cherry
Author: Seb Arnold
Author-email: smr.arnold@gmail.com
License: License :: OSI Approved :: Apache Software License
Download-URL: https://github.com/learnables/cherry/archive/0.2.0.zip
Platform: UNKNOWN
License-File: LICENSE
